{
	"user": [
		{
			"name": "string",
			"email": "string",
			"password": "string",
			"projects": [
				{
					"project1": "string"
				}
			]
		}
	],
	"project": [
		{
			"title": "string",
			"description": "string",
			"deadline": "date",
			"author": "string",
			"associates": [
				{
					"assoc": "string"
				}
			],
			"tasks": [
				{
					"todo": [
						{
							"title": "string",
							"status": "boolean",
							"items": [
								{
									"itemOne": "string"
								}
							]
						}
					],
					"notes": [
						{
							"title": "string",
							"content": "string"
						}
					]
				}
			]
		}
	]
}